django_pluggables-0.2.0.dist-info/DESCRIPTION.rst
django_pluggables-0.2.0.dist-info/METADATA
django_pluggables-0.2.0.dist-info/RECORD
django_pluggables-0.2.0.dist-info/WHEEL
django_pluggables-0.2.0.dist-info/metadata.json
django_pluggables-0.2.0.dist-info/top_level.txt
pluggables/__init__.py
pluggables/models.py
pluggables/templatetags/__init__.py
pluggables/templatetags/pluggables.py
pluggables/utils/__init__.py
pluggables/utils/picklefield.py
