Metadata-Version: 2.0
Name: django-pluggables
Version: 0.2.0
Summary: A design pattern for Django that allows you to build "Pluggable" Reusable Applications
Home-page: http://github.com/nowells/django-pluggables/
Author: Nowell Strite
Author-email: nowell@strite.org
License: MIT
Platform: any
Classifier: Development Status :: 4 - Beta
Classifier: Environment :: Web Environment
Classifier: Intended Audience :: Developers
Classifier: License :: OSI Approved :: MIT License
Classifier: Operating System :: OS Independent
Classifier: Programming Language :: Python
Classifier: Topic :: Utilities
